CHANGELOG
COPYRIGHT
INSTALL
LICENSE
MANIFEST.in
README.md
TODO
company.xml
header_A4.odt
invoice.odt
invoice.xml
party.xml
pos.xml
setup.py
./01_updates.py
./__init__.py
./actividades.py
./address.py
./afip_auth.py
./afip_codigo_actividad.py
./company.py
./company.xml
./header_A4.odt
./incoterms.py
./invoice.odt
./invoice.py
./invoice.xml
./mapeo-paises-afip.py
./party.py
./party.xml
./pos.py
./pos.xml
./tryton.cfg
./locale/es_AR.po
./view/company_form.xml
./view/get_afip_data_start_view.xml
./view/invoice_form.xml
./view/invoice_tree.xml
./view/party_form.xml
./view/pos_form.xml
./view/pos_sequence_form.xml
./view/pos_sequence_tree.xml
./view/pos_tree.xml
./view/transaction_form.xml
./view/transaction_tree.xml
trytonar_account_invoice_ar.egg-info/PKG-INFO
trytonar_account_invoice_ar.egg-info/SOURCES.txt
trytonar_account_invoice_ar.egg-info/dependency_links.txt
trytonar_account_invoice_ar.egg-info/entry_points.txt
trytonar_account_invoice_ar.egg-info/not-zip-safe
trytonar_account_invoice_ar.egg-info/requires.txt
trytonar_account_invoice_ar.egg-info/top_level.txt