Metadata-Version: 1.1
Name: trytonar-account-invoice-ar
Version: 3.4.5
Summary: Tryton module to add account invoice (electronic/manual) localizacion for Argentina (AFIP)
Home-page: https://github.com/tryton-ar/account_invoice_ar
Author: tryton-ar
Author-email: UNKNOWN
License: GPL-3
Platform: UNKNOWN
Classifier: Development Status :: 4 - Beta
Classifier: Environment :: Plugins
Classifier: Framework :: Tryton
Classifier: Intended Audience :: Developers
Classifier: Intended Audience :: Financial and Insurance Industry
Classifier: Intended Audience :: Legal Industry
Classifier: License :: OSI Approved :: GNU General Public License (GPL)
Classifier: Natural Language :: English
Classifier: Natural Language :: Spanish
Classifier: Operating System :: OS Independent
Classifier: Programming Language :: Python :: 2.7
Classifier: Topic :: Office/Business
Classifier: Topic :: Office/Business :: Financial :: Accounting
